BlackjackSim/BlackJackSim.py
BlackjackSim/PlayStrategy.py
BlackjackSim/UserQueryCommandCards.py
BlackjackSim/__init__.py
BlackjackSim/main.py
blackjacksim-1.0.0.dist-info/METADATA
blackjacksim-1.0.0.dist-info/WHEEL
blackjacksim-1.0.0.dist-info/entry_points.txt
blackjacksim-1.0.0.dist-info/licenses/LICENSE
blackjacksim-1.0.0.dist-info/RECORD
